Metadata-Version: 2.1
Name: dataplatform-path-generator
Version: 0.0.2
Summary: A library for generating the path to write files to in cloud storage
Home-page: UNKNOWN
Author: Yash Vaidya
License: Apache 2.0
Platform: UNKNOWN
Classifier: License :: OSI Approved :: Apache Software License
Classifier: Programming Language :: Python :: 3.7
Classifier: Programming Language :: Python :: 3.8
Classifier: Programming Language :: Python :: 3.9
